xpublish_opendap/__init__.py
xpublish_opendap/_version.py
xpublish_opendap/dap_xarray.py
xpublish_opendap/plugin.py
xpublish_opendap-0.2.0.dist-info/licenses/LICENSE.txt
xpublish_opendap-0.2.0.dist-info/METADATA
xpublish_opendap-0.2.0.dist-info/WHEEL
xpublish_opendap-0.2.0.dist-info/entry_points.txt
xpublish_opendap-0.2.0.dist-info/top_level.txt
xpublish_opendap-0.2.0.dist-info/RECORD
