Metadata-Version: 2.4
Name: xpublish_opendap
Version: 0.2.0
Summary: OpenDAP plugin for Xpublish
License: Copyright 2017 AUTHOR NAME
Project-URL: Homepage, https://github.com/xpublish-community/xpublish-opendap/
Keywords: xarray,xpublish,opendap
Classifier: Development Status :: 5 - Production/Stable
Classifier: Intended Audience :: Science/Research
Classifier: Operating System :: OS Independent
Classifier: License :: OSI Approved :: BSD License
Classifier: Programming Language :: Python
Classifier: Programming Language :: Python :: 3
Classifier: Programming Language :: Python :: 3.11
Classifier: Programming Language :: Python :: 3.12
Classifier: Topic :: Scientific/Engineering
Requires-Python: >=3.11
License-File: LICENSE.txt
Requires-Dist: opendap-protocol<1.2.0
Requires-Dist: xarray
Requires-Dist: xpublish>=0.4.0
Dynamic: license-file
